{
  "panels": {
    "1508484691467042946": {
      "언어역할": {
        "name": "언어역할",
        "description": "여러분이 주로 사용하는 언어를 골라주세요!",
        "items": [
          {
            "roleId": "1508652584766935190",
            "roleName": "Java",
            "emoji": "<:__:1508649357669564497>"
          },
          {
            "roleId": "1508652883304910868",
            "roleName": "JavaScript",
            "emoji": "<:__:1508649416591020194>"
          },
          {
            "roleId": "1508655514572029992",
            "roleName": "C",
            "emoji": "<:cplusplus:1508655334137397258>"
          },
          {
            "roleId": "1508655594918379620",
            "roleName": "python",
            "emoji": "<:python:1508654412669648986>"
          },
          {
            "roleId": "1508655648315932783",
            "roleName": "Kotlin",
            "emoji": "<:Kotlin:1508654271153831946>"
          }
        ]
      },
      "언어역할\n!패널 설명 언어역할 | 여러분이 주로 사용하는 언어를 골라주세요!": {
        "name": "언어역할\n!패널 설명 언어역할 | 여러분이 주로 사용하는 언어를 골라주세요!",
        "description": "원하는 이모지를 클릭하면 역할이 부여됩니다.",
        "items": []
      }
    }
  },
  "publishedMessages": {
    "1508653014653862050": {
      "guildId": "1508484691467042946",
      "channelId": "1508644004173185106",
      "panelName": "언어역할"
    }
  }
}